LICENSE
MANIFEST.in
README.md
requirements.txt
setup.py
minds/__about__.py
minds/__init__.py
minds/client.py
minds/exceptions.py
minds/minds.py
minds/rest_api.py
minds/datasources/__init__.py
minds/datasources/datasources.py
minds/knowledge_bases/__init__.py
minds/knowledge_bases/knowledge_bases.py
minds/knowledge_bases/preprocessing.py
minds_sdk.egg-info/PKG-INFO
minds_sdk.egg-info/SOURCES.txt
minds_sdk.egg-info/dependency_links.txt
minds_sdk.egg-info/requires.txt
minds_sdk.egg-info/top_level.txt