Metadata-Version: 2.4
Name: minds_sdk
Version: 2.0.1
Summary: An AI-Data Mind is an LLM with the built-in power to answer data questions for Agents
Home-page: https://github.com/mindsdb/minds_python_sdk
Download-URL: https://pypi.org/project/mindsdb/
Author: MindsDB Inc
Author-email: hello@mindsdb.com
Classifier: Programming Language :: Python :: 3
Classifier: Operating System :: OS Independent
Requires-Python: >=3.8
License-File: LICENSE
Requires-Dist: pydantic>=2.10
Requires-Dist: requests
Requires-Dist: openai>=1.75.0
Dynamic: author
Dynamic: author-email
Dynamic: classifier
Dynamic: description
Dynamic: description-content-type
Dynamic: download-url
Dynamic: home-page
Dynamic: license-file
Dynamic: requires-dist
Dynamic: requires-python
Dynamic: summary
